aioamqp-stubs/__init__.pyi
aioamqp-stubs/channel.pyi
aioamqp-stubs/constants.pyi
aioamqp-stubs/envelope.pyi
aioamqp-stubs/exceptions.pyi
aioamqp-stubs/frame.pyi
aioamqp-stubs/properties.pyi
aioamqp-stubs/protocol.pyi
aioamqp-stubs/version.pyi
aioamqp_stubs-0.15.dist-info/LICENSE
aioamqp_stubs-0.15.dist-info/METADATA
aioamqp_stubs-0.15.dist-info/WHEEL
aioamqp_stubs-0.15.dist-info/RECORD
