Metadata-Version: 2.3
Name: aioamqp-stubs
Version: 0.15
Summary: Stubs for aioamqp
License: MIT
Keywords: aioamqp,typing,types,stubs,mypy
Author: guitvcer
Author-email: abdrakhman.galaxy.s2@gmail.com
Requires-Python: >=3.10,<4.0
Classifier: Development Status :: 5 - Production/Stable
Classifier: Intended Audience :: Developers
Classifier: Programming Language :: Python :: 3
Classifier: Programming Language :: Python :: 3.10
Classifier: Programming Language :: Python :: 3.11
Classifier: Programming Language :: Python :: 3.12
Classifier: Programming Language :: Python :: 3.13
Classifier: Operating System :: OS Independent
Classifier: Topic :: Software Development :: Libraries :: Python Modules
Classifier: Typing :: Typed
Requires-Dist: aioamqp (>=0.15.0,<0.16.0)
Project-URL: Repository, https://github.com/guitvcer/aioamqp-stubs
